<?xml version="1.0" encoding="UTF-8"?>
<itemslist xmlns:xsi="http://www.w3.org/2001/XMLSchema-instance" xsi:noNamespaceSchemaLocation="items-schema.xsd">
<item cpu_vendor="Intel" cpu_codename="Sapphire Rapids" cpu_model="Max 9480" cpu_cores="56" cpu_feature_size="7e-9" cpu_frequency="1.9" cpu_flops_per_cycle="32" cpu_l3_cache="112.5" cpu_acp="244" cpu_tdp="350" node_power="+350" node_cpu_count="+1" node_cost="+12980">Intel Sapphire Rapids Max 9480</item>
<item cpu_vendor="Intel" cpu_codename="Sapphire Rapids" cpu_model="Max 9470" cpu_cores="52" cpu_feature_size="7e-9" cpu_frequency="2.0" cpu_flops_per_cycle="32" cpu_l3_cache="105.0" cpu_acp="244" cpu_tdp="350" node_power="+350" node_cpu_count="+1" node_cost="+11590">Intel Sapphire Rapids Max 9470</item>
<item cpu_vendor="Intel" cpu_codename="Sapphire Rapids" cpu_model="Max 9468" cpu_cores="48" cpu_feature_size="7e-9" cpu_frequency="2.1" cpu_flops_per_cycle="32" cpu_l3_cache="105.0" cpu_acp="244" cpu_tdp="350" node_power="+350" node_cpu_count="+1" node_cost="+9900">Intel Sapphire Rapids Max 9468</item>
<item cpu_vendor="Intel" cpu_codename="Sapphire Rapids" cpu_model="Max 9460" cpu_cores="40" cpu_feature_size="7e-9" cpu_frequency="2.2" cpu_flops_per_cycle="32" cpu_l3_cache="97.5" cpu_acp="244" cpu_tdp="350" node_power="+350" node_cpu_count="+1" node_cost="+8750">Intel Sapphire Rapids Max 9460</item>
<item cpu_vendor="Intel" cpu_codename="Sapphire Rapids" cpu_model="Max 9462" cpu_cores="32" cpu_feature_size="7e-9" cpu_frequency="2.7" cpu_flops_per_cycle="32" cpu_l3_cache="75.0" cpu_acp="244" cpu_tdp="350" node_power="+350" node_cpu_count="+1" node_cost="+7995">Intel Sapphire Rapids Max 9462</item>
<item cpu_vendor="Intel" cpu_codename="Sapphire Rapids" cpu_model="Platinum 8490H" cpu_cores="60" cpu_feature_size="7e-9" cpu_frequency="1.9" cpu_flops_per_cycle="32" cpu_l3_cache="112.5" cpu_acp="244" cpu_tdp="350" node_power="+350" node_cpu_count="+1" node_cost="+17000">Intel Sapphire Rapids Platinum 8490H</item>
<item cpu_vendor="Intel" cpu_codename="Sapphire Rapids" cpu_model="Platinum 8480+" cpu_cores="56" cpu_feature_size="7e-9" cpu_frequency="2.0" cpu_flops_per_cycle="32" cpu_l3_cache="105.0" cpu_acp="244" cpu_tdp="350" node_power="+350" node_cpu_count="+1" node_cost="+10710">Intel Sapphire Rapids Platinum 8480+</item>
<item cpu_vendor="Intel" cpu_codename="Sapphire Rapids" cpu_model="Platinum 8470Q" cpu_cores="52" cpu_feature_size="7e-9" cpu_frequency="2.1" cpu_flops_per_cycle="32" cpu_l3_cache="105.0" cpu_acp="244" cpu_tdp="350" node_power="+350" node_cpu_count="+1" node_cost="+9410">Intel Sapphire Rapids Platinum 8470Q</item>
<item cpu_vendor="Intel" cpu_codename="Sapphire Rapids" cpu_model="Platinum 8470N" cpu_cores="52" cpu_feature_size="7e-9" cpu_frequency="1.7" cpu_flops_per_cycle="32" cpu_l3_cache="97.5" cpu_acp="210" cpu_tdp="300" node_power="+300" node_cpu_count="+1" node_cost="+9520">Intel Sapphire Rapids Platinum 8470N</item>
<item cpu_vendor="Intel" cpu_codename="Sapphire Rapids" cpu_model="Platinum 8470" cpu_cores="52" cpu_feature_size="7e-9" cpu_frequency="2.0" cpu_flops_per_cycle="32" cpu_l3_cache="105.0" cpu_acp="244" cpu_tdp="350" node_power="+350" node_cpu_count="+1" node_cost="+9359">Intel Sapphire Rapids Platinum 8470</item>
<item cpu_vendor="Intel" cpu_codename="Sapphire Rapids" cpu_model="Platinum 8468V" cpu_cores="48" cpu_feature_size="7e-9" cpu_frequency="2.4" cpu_flops_per_cycle="32" cpu_l3_cache="97.5" cpu_acp="230" cpu_tdp="330" node_power="+330" node_cpu_count="+1" node_cost="+7121">Intel Sapphire Rapids Platinum 8468V</item>
<item cpu_vendor="Intel" cpu_codename="Sapphire Rapids" cpu_model="Platinum 8468" cpu_cores="48" cpu_feature_size="7e-9" cpu_frequency="2.1" cpu_flops_per_cycle="32" cpu_l3_cache="105.0" cpu_acp="244" cpu_tdp="350" node_power="+350" node_cpu_count="+1" node_cost="+7214">Intel Sapphire Rapids Platinum 8468</item>
<item cpu_vendor="Intel" cpu_codename="Sapphire Rapids" cpu_model="Platinum 8462Y+" cpu_cores="32" cpu_feature_size="7e-9" cpu_frequency="2.8" cpu_flops_per_cycle="32" cpu_l3_cache="60.0" cpu_acp="210" cpu_tdp="300" node_power="+300" node_cpu_count="+1" node_cost="+5945">Intel Sapphire Rapids Platinum 8462Y+</item>
<item cpu_vendor="Intel" cpu_codename="Sapphire Rapids" cpu_model="Platinum 8460Y+" cpu_cores="40" cpu_feature_size="7e-9" cpu_frequency="2.0" cpu_flops_per_cycle="32" cpu_l3_cache="105.0" cpu_acp="210" cpu_tdp="300" node_power="+300" node_cpu_count="+1" node_cost="+5558">Intel Sapphire Rapids Platinum 8460Y+</item>
<item cpu_vendor="Intel" cpu_codename="Sapphire Rapids" cpu_model="Platinum 8460H" cpu_cores="40" cpu_feature_size="7e-9" cpu_frequency="2.2" cpu_flops_per_cycle="32" cpu_l3_cache="105.0" cpu_acp="230" cpu_tdp="330" node_power="+330" node_cpu_count="+1" node_cost="+10710">Intel Sapphire Rapids Platinum 8460H</item>
<item cpu_vendor="Intel" cpu_codename="Sapphire Rapids" cpu_model="Platinum 8458P" cpu_cores="44" cpu_feature_size="7e-9" cpu_frequency="2.7" cpu_flops_per_cycle="32" cpu_l3_cache="82.5" cpu_acp="244" cpu_tdp="350" node_power="+350" node_cpu_count="+1" node_cost="+7121">Intel Sapphire Rapids Platinum 8458P</item>
<item cpu_vendor="Intel" cpu_codename="Sapphire Rapids" cpu_model="Platinum 8454H" cpu_cores="32" cpu_feature_size="7e-9" cpu_frequency="2.1" cpu_flops_per_cycle="32" cpu_l3_cache="82.5" cpu_acp="189" cpu_tdp="270" node_power="+270" node_cpu_count="+1" node_cost="+6540">Intel Sapphire Rapids Platinum 8454H</item>
<item cpu_vendor="Intel" cpu_codename="Sapphire Rapids" cpu_model="Platinum 8452Y" cpu_cores="36" cpu_feature_size="7e-9" cpu_frequency="2.0" cpu_flops_per_cycle="32" cpu_l3_cache="67.5" cpu_acp="210" cpu_tdp="300" node_power="+300" node_cpu_count="+1" node_cost="+3995">Intel Sapphire Rapids Platinum 8452Y</item>
<item cpu_vendor="Intel" cpu_codename="Sapphire Rapids" cpu_model="Platinum 8450H" cpu_cores="28" cpu_feature_size="7e-9" cpu_frequency="2.0" cpu_flops_per_cycle="32" cpu_l3_cache="75.0" cpu_acp="175" cpu_tdp="250" node_power="+250" node_cpu_count="+1" node_cost="+4708">Intel Sapphire Rapids Platinum 8450H</item>
<item cpu_vendor="Intel" cpu_codename="Sapphire Rapids" cpu_model="Platinum 8444H" cpu_cores="16" cpu_feature_size="7e-9" cpu_frequency="2.9" cpu_flops_per_cycle="32" cpu_l3_cache="45.0" cpu_acp="189" cpu_tdp="270" node_power="+270" node_cpu_count="+1" node_cost="+4234">Intel Sapphire Rapids Platinum 8444H</item>
<item cpu_vendor="Intel" cpu_codename="Sapphire Rapids" cpu_model="Gold 6458Q" cpu_cores="32" cpu_feature_size="7e-9" cpu_frequency="3.1" cpu_flops_per_cycle="32" cpu_l3_cache="60.0" cpu_acp="244" cpu_tdp="350" node_power="+350" node_cpu_count="+1" node_cost="+6416">Intel Sapphire Rapids Gold 6458Q</item>
<item cpu_vendor="Intel" cpu_codename="Sapphire Rapids" cpu_model="Gold 6454S" cpu_cores="32" cpu_feature_size="7e-9" cpu_frequency="2.2" cpu_flops_per_cycle="32" cpu_l3_cache="60.0" cpu_acp="189" cpu_tdp="270" node_power="+270" node_cpu_count="+1" node_cost="+3157">Intel Sapphire Rapids Gold 6454S</item>
<item cpu_vendor="Intel" cpu_codename="Sapphire Rapids" cpu_model="Gold 6448Y" cpu_cores="32" cpu_feature_size="7e-9" cpu_frequency="2.1" cpu_flops_per_cycle="32" cpu_l3_cache="60.0" cpu_acp="157" cpu_tdp="225" node_power="+225" node_cpu_count="+1" node_cost="+3583">Intel Sapphire Rapids Gold 6448Y</item>
<item cpu_vendor="Intel" cpu_codename="Sapphire Rapids" cpu_model="Gold 6448H" cpu_cores="32" cpu_feature_size="7e-9" cpu_frequency="2.4" cpu_flops_per_cycle="32" cpu_l3_cache="60.0" cpu_acp="175" cpu_tdp="250" node_power="+250" node_cpu_count="+1" node_cost="+3658">Intel Sapphire Rapids Gold 6448H</item>
<item cpu_vendor="Intel" cpu_codename="Sapphire Rapids" cpu_model="Gold 6444Y" cpu_cores="16" cpu_feature_size="7e-9" cpu_frequency="3.6" cpu_flops_per_cycle="32" cpu_l3_cache="45.0" cpu_acp="189" cpu_tdp="270" node_power="+270" node_cpu_count="+1" node_cost="+3622">Intel Sapphire Rapids Gold 6444Y</item>
<item cpu_vendor="Intel" cpu_codename="Sapphire Rapids" cpu_model="Gold 6442Y" cpu_cores="24" cpu_feature_size="7e-9" cpu_frequency="2.6" cpu_flops_per_cycle="32" cpu_l3_cache="60.0" cpu_acp="157" cpu_tdp="225" node_power="+225" node_cpu_count="+1" node_cost="+2878">Intel Sapphire Rapids Gold 6442Y</item>
<item cpu_vendor="Intel" cpu_codename="Sapphire Rapids" cpu_model="Gold 6438Y+" cpu_cores="32" cpu_feature_size="7e-9" cpu_frequency="2.0" cpu_flops_per_cycle="32" cpu_l3_cache="60.0" cpu_acp="143" cpu_tdp="205" node_power="+205" node_cpu_count="+1" node_cost="+3141">Intel Sapphire Rapids Gold 6438Y+</item>
<item cpu_vendor="Intel" cpu_codename="Sapphire Rapids" cpu_model="Gold 6438N" cpu_cores="32" cpu_feature_size="7e-9" cpu_frequency="2.0" cpu_flops_per_cycle="32" cpu_l3_cache="60.0" cpu_acp="143" cpu_tdp="205" node_power="+205" node_cpu_count="+1" node_cost="+3351">Intel Sapphire Rapids Gold 6438N</item>
<item cpu_vendor="Intel" cpu_codename="Sapphire Rapids" cpu_model="Gold 6438M" cpu_cores="32" cpu_feature_size="7e-9" cpu_frequency="2.2" cpu_flops_per_cycle="32" cpu_l3_cache="60.0" cpu_acp="143" cpu_tdp="205" node_power="+205" node_cpu_count="+1" node_cost="+3273">Intel Sapphire Rapids Gold 6438M</item>
<item cpu_vendor="Intel" cpu_codename="Sapphire Rapids" cpu_model="Gold 6434H" cpu_cores="8" cpu_feature_size="7e-9" cpu_frequency="3.7" cpu_flops_per_cycle="32" cpu_l3_cache="22.5" cpu_acp="136" cpu_tdp="195" node_power="+195" node_cpu_count="+1" node_cost="+3070">Intel Sapphire Rapids Gold 6434H</item>
<item cpu_vendor="Intel" cpu_codename="Sapphire Rapids" cpu_model="Gold 6434" cpu_cores="8" cpu_feature_size="7e-9" cpu_frequency="3.7" cpu_flops_per_cycle="32" cpu_l3_cache="22.5" cpu_acp="136" cpu_tdp="195" node_power="+195" node_cpu_count="+1" node_cost="+2607">Intel Sapphire Rapids Gold 6434</item>
<item cpu_vendor="Intel" cpu_codename="Sapphire Rapids" cpu_model="Gold 6430" cpu_cores="32" cpu_feature_size="7e-9" cpu_frequency="2.1" cpu_flops_per_cycle="32" cpu_l3_cache="60.0" cpu_acp="189" cpu_tdp="270" node_power="+270" node_cpu_count="+1" node_cost="+2128">Intel Sapphire Rapids Gold 6430</item>
<item cpu_vendor="Intel" cpu_codename="Sapphire Rapids" cpu_model="Gold 6428N" cpu_cores="32" cpu_feature_size="7e-9" cpu_frequency="1.8" cpu_flops_per_cycle="32" cpu_l3_cache="60.0" cpu_acp="129" cpu_tdp="185" node_power="+185" node_cpu_count="+1" node_cost="+3200">Intel Sapphire Rapids Gold 6428N</item>
<item cpu_vendor="Intel" cpu_codename="Sapphire Rapids" cpu_model="Gold 6426Y" cpu_cores="16" cpu_feature_size="7e-9" cpu_frequency="2.5" cpu_flops_per_cycle="32" cpu_l3_cache="37.5" cpu_acp="129" cpu_tdp="185" node_power="+185" node_cpu_count="+1" node_cost="+1517">Intel Sapphire Rapids Gold 6426Y</item>
<item cpu_vendor="Intel" cpu_codename="Sapphire Rapids" cpu_model="Gold 6418H" cpu_cores="24" cpu_feature_size="7e-9" cpu_frequency="2.1" cpu_flops_per_cycle="32" cpu_l3_cache="60.0" cpu_acp="129" cpu_tdp="185" node_power="+185" node_cpu_count="+1" node_cost="+2065">Intel Sapphire Rapids Gold 6418H</item>
<item cpu_vendor="Intel" cpu_codename="Sapphire Rapids" cpu_model="Gold 6416H" cpu_cores="18" cpu_feature_size="7e-9" cpu_frequency="2.2" cpu_flops_per_cycle="32" cpu_l3_cache="45.0" cpu_acp="115" cpu_tdp="165" node_power="+165" node_cpu_count="+1" node_cost="+1444">Intel Sapphire Rapids Gold 6416H</item>
<item cpu_vendor="Intel" cpu_codename="Sapphire Rapids" cpu_model="Gold 5420+" cpu_cores="28" cpu_feature_size="7e-9" cpu_frequency="2.0" cpu_flops_per_cycle="32" cpu_l3_cache="52.5" cpu_acp="143" cpu_tdp="205" node_power="+205" node_cpu_count="+1" node_cost="+1848">Intel Sapphire Rapids Gold 5420+</item>
<item cpu_vendor="Intel" cpu_codename="Sapphire Rapids" cpu_model="Gold 5418Y" cpu_cores="24" cpu_feature_size="7e-9" cpu_frequency="2.0" cpu_flops_per_cycle="32" cpu_l3_cache="45.0" cpu_acp="129" cpu_tdp="185" node_power="+185" node_cpu_count="+1" node_cost="+1483">Intel Sapphire Rapids Gold 5418Y</item>
<item cpu_vendor="Intel" cpu_codename="Sapphire Rapids" cpu_model="Gold 5418N" cpu_cores="24" cpu_feature_size="7e-9" cpu_frequency="1.8" cpu_flops_per_cycle="32" cpu_l3_cache="45.0" cpu_acp="115" cpu_tdp="165" node_power="+165" node_cpu_count="+1" node_cost="+1664">Intel Sapphire Rapids Gold 5418N</item>
<item cpu_vendor="Intel" cpu_codename="Sapphire Rapids" cpu_model="Gold 5416S" cpu_cores="16" cpu_feature_size="7e-9" cpu_frequency="2.0" cpu_flops_per_cycle="32" cpu_l3_cache="30.0" cpu_acp="105" cpu_tdp="150" node_power="+150" node_cpu_count="+1" node_cost="+944">Intel Sapphire Rapids Gold 5416S</item>
<item cpu_vendor="Intel" cpu_codename="Sapphire Rapids" cpu_model="Gold 5415+" cpu_cores="8" cpu_feature_size="7e-9" cpu_frequency="2.9" cpu_flops_per_cycle="32" cpu_l3_cache="22.5" cpu_acp="105" cpu_tdp="150" node_power="+150" node_cpu_count="+1" node_cost="+1066">Intel Sapphire Rapids Gold 5415+</item>
<item cpu_vendor="Intel" cpu_codename="Sapphire Rapids" cpu_model="Silver 4416+" cpu_cores="20" cpu_feature_size="7e-9" cpu_frequency="2.0" cpu_flops_per_cycle="32" cpu_l3_cache="37.5" cpu_acp="115" cpu_tdp="165" node_power="+165" node_cpu_count="+1" node_cost="+1176">Intel Sapphire Rapids Silver 4416+</item>
<item cpu_vendor="Intel" cpu_codename="Sapphire Rapids" cpu_model="Silver 4410Y" cpu_cores="12" cpu_feature_size="7e-9" cpu_frequency="2.0" cpu_flops_per_cycle="32" cpu_l3_cache="30.0" cpu_acp="105" cpu_tdp="150" node_power="+150" node_cpu_count="+1" node_cost="+563">Intel Sapphire Rapids Silver 4410Y</item>
<item cpu_vendor="Intel" cpu_codename="Sapphire Rapids" cpu_model="Silver 4410T" cpu_cores="10" cpu_feature_size="7e-9" cpu_frequency="2.7" cpu_flops_per_cycle="32" cpu_l3_cache="26.25" cpu_acp="105" cpu_tdp="150" node_power="+150" node_cpu_count="+1" node_cost="+624">Intel Sapphire Rapids Silver 4410T</item>
</itemslist>